<annotation>
        <folder>FOLDER</folder>
        <filename>022412615.jpg</filename>
        <path>data/scenes/val\022412615.jpg</path>
        <source>
                <database>Unknown</database>
        </source>
        <size>
                <width>720</width>
                <height>720</height>
                <depth>3</depth>
        </size>
 <object>
                <name>S10</name>
                <pose>Unspecified</pose>
                <truncated>0</truncated>
                <difficult>0</difficult>
                <bndbox>
                        <xmin>415</xmin>
                        <ymin>330</ymin>
                        <xmax>439</xmax>
                        <ymax>358</ymax>
                </bndbox>
        </object>
 <object>
                <name>E8</name>
                <pose>Unspecified</pose>
                <truncated>0</truncated>
                <difficult>0</difficult>
                <bndbox>
                        <xmin>384</xmin>
                        <ymin>306</ymin>
                        <xmax>416</xmax>
                        <ymax>338</ymax>
                </bndbox>
        </object>
 <object>
                <name>GO</name>
                <pose>Unspecified</pose>
                <truncated>0</truncated>
                <difficult>0</difficult>
                <bndbox>
                        <xmin>344</xmin>
                        <ymin>267</ymin>
                        <xmax>378</xmax>
                        <ymax>296</ymax>
                </bndbox>
        </object>
 <object>
                <name>GO</name>
                <pose>Unspecified</pose>
                <truncated>0</truncated>
                <difficult>0</difficult>
                <bndbox>
                        <xmin>442</xmin>
                        <ymin>66</ymin>
                        <xmax>480</xmax>
                        <ymax>97</ymax>
                </bndbox>
        </object>
</annotation>        
