<annotation>
        <folder>FOLDER</folder>
        <filename>024785890.jpg</filename>
        <path>data/scenes/val\024785890.jpg</path>
        <source>
                <database>Unknown</database>
        </source>
        <size>
                <width>720</width>
                <height>720</height>
                <depth>3</depth>
        </size>
 <object>
                <name>G8</name>
                <pose>Unspecified</pose>
                <truncated>0</truncated>
                <difficult>0</difficult>
                <bndbox>
                        <xmin>182</xmin>
                        <ymin>440</ymin>
                        <xmax>233</xmax>
                        <ymax>469</ymax>
                </bndbox>
        </object>
 <object>
                <name>G10</name>
                <pose>Unspecified</pose>
                <truncated>0</truncated>
                <difficult>0</difficult>
                <bndbox>
                        <xmin>161</xmin>
                        <ymin>391</ymin>
                        <xmax>211</xmax>
                        <ymax>414</ymax>
                </bndbox>
        </object>
 <object>
                <name>GO</name>
                <pose>Unspecified</pose>
                <truncated>0</truncated>
                <difficult>0</difficult>
                <bndbox>
                        <xmin>160</xmin>
                        <ymin>308</ymin>
                        <xmax>219</xmax>
                        <ymax>332</ymax>
                </bndbox>
        </object>
 <object>
                <name>GO</name>
                <pose>Unspecified</pose>
                <truncated>0</truncated>
                <difficult>0</difficult>
                <bndbox>
                        <xmin>477</xmin>
                        <ymin>179</ymin>
                        <xmax>537</xmax>
                        <ymax>205</ymax>
                </bndbox>
        </object>
</annotation>        
