<annotation>
        <folder>FOLDER</folder>
        <filename>048048118.jpg</filename>
        <path>data/scenes/val\048048118.jpg</path>
        <source>
                <database>Unknown</database>
        </source>
        <size>
                <width>720</width>
                <height>720</height>
                <depth>3</depth>
        </size>
 <object>
                <name>HA</name>
                <pose>Unspecified</pose>
                <truncated>0</truncated>
                <difficult>0</difficult>
                <bndbox>
                        <xmin>459</xmin>
                        <ymin>245</ymin>
                        <xmax>517</xmax>
                        <ymax>273</ymax>
                </bndbox>
        </object>
 <object>
                <name>EO</name>
                <pose>Unspecified</pose>
                <truncated>0</truncated>
                <difficult>0</difficult>
                <bndbox>
                        <xmin>454</xmin>
                        <ymin>291</ymin>
                        <xmax>499</xmax>
                        <ymax>321</ymax>
                </bndbox>
        </object>
 <object>
                <name>GU</name>
                <pose>Unspecified</pose>
                <truncated>0</truncated>
                <difficult>0</difficult>
                <bndbox>
                        <xmin>423</xmin>
                        <ymin>354</ymin>
                        <xmax>465</xmax>
                        <ymax>392</ymax>
                </bndbox>
        </object>
 <object>
                <name>GU</name>
                <pose>Unspecified</pose>
                <truncated>0</truncated>
                <difficult>0</difficult>
                <bndbox>
                        <xmin>75</xmin>
                        <ymin>308</ymin>
                        <xmax>116</xmax>
                        <ymax>347</ymax>
                </bndbox>
        </object>
</annotation>        
