<annotation>
        <folder>FOLDER</folder>
        <filename>052278887.jpg</filename>
        <path>data/scenes/train\052278887.jpg</path>
        <source>
                <database>Unknown</database>
        </source>
        <size>
                <width>720</width>
                <height>720</height>
                <depth>3</depth>
        </size>
 <object>
                <name>GO</name>
                <pose>Unspecified</pose>
                <truncated>0</truncated>
                <difficult>0</difficult>
                <bndbox>
                        <xmin>430</xmin>
                        <ymin>262</ymin>
                        <xmax>479</xmax>
                        <ymax>292</ymax>
                </bndbox>
        </object>
 <object>
                <name>G10</name>
                <pose>Unspecified</pose>
                <truncated>0</truncated>
                <difficult>0</difficult>
                <bndbox>
                        <xmin>417</xmin>
                        <ymin>303</ymin>
                        <xmax>460</xmax>
                        <ymax>345</ymax>
                </bndbox>
        </object>
 <object>
                <name>G7</name>
                <pose>Unspecified</pose>
                <truncated>0</truncated>
                <difficult>0</difficult>
                <bndbox>
                        <xmin>373</xmin>
                        <ymin>342</ymin>
                        <xmax>415</xmax>
                        <ymax>395</ymax>
                </bndbox>
        </object>
 <object>
                <name>G7</name>
                <pose>Unspecified</pose>
                <truncated>0</truncated>
                <difficult>0</difficult>
                <bndbox>
                        <xmin>46</xmin>
                        <ymin>231</ymin>
                        <xmax>87</xmax>
                        <ymax>281</ymax>
                </bndbox>
        </object>
</annotation>        
