<annotation>
        <folder>FOLDER</folder>
        <filename>181476094.jpg</filename>
        <path>data/scenes/train\181476094.jpg</path>
        <source>
                <database>Unknown</database>
        </source>
        <size>
                <width>720</width>
                <height>720</height>
                <depth>3</depth>
        </size>
 <object>
                <name>GU</name>
                <pose>Unspecified</pose>
                <truncated>0</truncated>
                <difficult>0</difficult>
                <bndbox>
                        <xmin>511</xmin>
                        <ymin>433</ymin>
                        <xmax>539</xmax>
                        <ymax>478</ymax>
                </bndbox>
        </object>
 <object>
                <name>EA</name>
                <pose>Unspecified</pose>
                <truncated>0</truncated>
                <difficult>0</difficult>
                <bndbox>
                        <xmin>440</xmin>
                        <ymin>419</ymin>
                        <xmax>476</xmax>
                        <ymax>465</ymax>
                </bndbox>
        </object>
 <object>
                <name>HU</name>
                <pose>Unspecified</pose>
                <truncated>0</truncated>
                <difficult>0</difficult>
                <bndbox>
                        <xmin>386</xmin>
                        <ymin>381</ymin>
                        <xmax>428</xmax>
                        <ymax>427</ymax>
                </bndbox>
        </object>
 <object>
                <name>HU</name>
                <pose>Unspecified</pose>
                <truncated>0</truncated>
                <difficult>0</difficult>
                <bndbox>
                        <xmin>434</xmin>
                        <ymin>39</ymin>
                        <xmax>480</xmax>
                        <ymax>88</ymax>
                </bndbox>
        </object>
</annotation>        
