<annotation>
        <folder>FOLDER</folder>
        <filename>251419154.jpg</filename>
        <path>data/scenes/train\251419154.jpg</path>
        <source>
                <database>Unknown</database>
        </source>
        <size>
                <width>720</width>
                <height>720</height>
                <depth>3</depth>
        </size>
 <object>
                <name>EA</name>
                <pose>Unspecified</pose>
                <truncated>0</truncated>
                <difficult>0</difficult>
                <bndbox>
                        <xmin>417</xmin>
                        <ymin>436</ymin>
                        <xmax>438</xmax>
                        <ymax>470</ymax>
                </bndbox>
        </object>
 <object>
                <name>EA</name>
                <pose>Unspecified</pose>
                <truncated>0</truncated>
                <difficult>0</difficult>
                <bndbox>
                        <xmin>587</xmin>
                        <ymin>591</ymin>
                        <xmax>607</xmax>
                        <ymax>622</ymax>
                </bndbox>
        </object>
 <object>
                <name>HU</name>
                <pose>Unspecified</pose>
                <truncated>0</truncated>
                <difficult>0</difficult>
                <bndbox>
                        <xmin>179</xmin>
                        <ymin>330</ymin>
                        <xmax>226</xmax>
                        <ymax>373</ymax>
                </bndbox>
        </object>
 <object>
                <name>HU</name>
                <pose>Unspecified</pose>
                <truncated>0</truncated>
                <difficult>0</difficult>
                <bndbox>
                        <xmin>279</xmin>
                        <ymin>1</ymin>
                        <xmax>329</xmax>
                        <ymax>46</ymax>
                </bndbox>
        </object>
</annotation>        
