<annotation>
        <folder>FOLDER</folder>
        <filename>314870940.jpg</filename>
        <path>data/scenes/train\314870940.jpg</path>
        <source>
                <database>Unknown</database>
        </source>
        <size>
                <width>720</width>
                <height>720</height>
                <depth>3</depth>
        </size>
 <object>
                <name>SO</name>
                <pose>Unspecified</pose>
                <truncated>0</truncated>
                <difficult>0</difficult>
                <bndbox>
                        <xmin>622</xmin>
                        <ymin>553</ymin>
                        <xmax>653</xmax>
                        <ymax>592</ymax>
                </bndbox>
        </object>
 <object>
                <name>EU</name>
                <pose>Unspecified</pose>
                <truncated>0</truncated>
                <difficult>0</difficult>
                <bndbox>
                        <xmin>378</xmin>
                        <ymin>310</ymin>
                        <xmax>415</xmax>
                        <ymax>348</ymax>
                </bndbox>
        </object>
 <object>
                <name>EU</name>
                <pose>Unspecified</pose>
                <truncated>0</truncated>
                <difficult>0</difficult>
                <bndbox>
                        <xmin>272</xmin>
                        <ymin>638</ymin>
                        <xmax>322</xmax>
                        <ymax>682</ymax>
                </bndbox>
        </object>
</annotation>        
