<annotation>
        <folder>FOLDER</folder>
        <filename>337672908.jpg</filename>
        <path>data/scenes/train\337672908.jpg</path>
        <source>
                <database>Unknown</database>
        </source>
        <size>
                <width>720</width>
                <height>720</height>
                <depth>3</depth>
        </size>
 <object>
                <name>HU</name>
                <pose>Unspecified</pose>
                <truncated>0</truncated>
                <difficult>0</difficult>
                <bndbox>
                        <xmin>194</xmin>
                        <ymin>208</ymin>
                        <xmax>231</xmax>
                        <ymax>235</ymax>
                </bndbox>
        </object>
 <object>
                <name>EK</name>
                <pose>Unspecified</pose>
                <truncated>0</truncated>
                <difficult>0</difficult>
                <bndbox>
                        <xmin>211</xmin>
                        <ymin>173</ymin>
                        <xmax>246</xmax>
                        <ymax>206</ymax>
                </bndbox>
        </object>
 <object>
                <name>GU</name>
                <pose>Unspecified</pose>
                <truncated>0</truncated>
                <difficult>0</difficult>
                <bndbox>
                        <xmin>249</xmin>
                        <ymin>144</ymin>
                        <xmax>273</xmax>
                        <ymax>168</ymax>
                </bndbox>
        </object>
 <object>
                <name>GU</name>
                <pose>Unspecified</pose>
                <truncated>0</truncated>
                <difficult>0</difficult>
                <bndbox>
                        <xmin>458</xmin>
                        <ymin>231</ymin>
                        <xmax>483</xmax>
                        <ymax>260</ymax>
                </bndbox>
        </object>
</annotation>        
