<annotation>
        <folder>FOLDER</folder>
        <filename>359890347.jpg</filename>
        <path>data/scenes/train\359890347.jpg</path>
        <source>
                <database>Unknown</database>
        </source>
        <size>
                <width>720</width>
                <height>720</height>
                <depth>3</depth>
        </size>
 <object>
                <name>EA</name>
                <pose>Unspecified</pose>
                <truncated>0</truncated>
                <difficult>0</difficult>
                <bndbox>
                        <xmin>537</xmin>
                        <ymin>393</ymin>
                        <xmax>557</xmax>
                        <ymax>429</ymax>
                </bndbox>
        </object>
 <object>
                <name>EA</name>
                <pose>Unspecified</pose>
                <truncated>0</truncated>
                <difficult>0</difficult>
                <bndbox>
                        <xmin>404</xmin>
                        <ymin>209</ymin>
                        <xmax>423</xmax>
                        <ymax>250</ymax>
                </bndbox>
        </object>
 <object>
                <name>E7</name>
                <pose>Unspecified</pose>
                <truncated>0</truncated>
                <difficult>0</difficult>
                <bndbox>
                        <xmin>93</xmin>
                        <ymin>30</ymin>
                        <xmax>118</xmax>
                        <ymax>89</ymax>
                </bndbox>
        </object>
 <object>
                <name>E7</name>
                <pose>Unspecified</pose>
                <truncated>0</truncated>
                <difficult>0</difficult>
                <bndbox>
                        <xmin>343</xmin>
                        <ymin>269</ymin>
                        <xmax>367</xmax>
                        <ymax>328</ymax>
                </bndbox>
        </object>
</annotation>        
