<annotation>
        <folder>FOLDER</folder>
        <filename>387198335.jpg</filename>
        <path>data/scenes/train\387198335.jpg</path>
        <source>
                <database>Unknown</database>
        </source>
        <size>
                <width>720</width>
                <height>720</height>
                <depth>3</depth>
        </size>
 <object>
                <name>S8</name>
                <pose>Unspecified</pose>
                <truncated>0</truncated>
                <difficult>0</difficult>
                <bndbox>
                        <xmin>521</xmin>
                        <ymin>261</ymin>
                        <xmax>563</xmax>
                        <ymax>282</ymax>
                </bndbox>
        </object>
 <object>
                <name>S8</name>
                <pose>Unspecified</pose>
                <truncated>0</truncated>
                <difficult>0</difficult>
                <bndbox>
                        <xmin>235</xmin>
                        <ymin>471</ymin>
                        <xmax>294</xmax>
                        <ymax>492</ymax>
                </bndbox>
        </object>
 <object>
                <name>EK</name>
                <pose>Unspecified</pose>
                <truncated>0</truncated>
                <difficult>0</difficult>
                <bndbox>
                        <xmin>449</xmin>
                        <ymin>389</ymin>
                        <xmax>470</xmax>
                        <ymax>435</ymax>
                </bndbox>
        </object>
 <object>
                <name>EK</name>
                <pose>Unspecified</pose>
                <truncated>0</truncated>
                <difficult>0</difficult>
                <bndbox>
                        <xmin>248</xmin>
                        <ymin>99</ymin>
                        <xmax>269</xmax>
                        <ymax>140</ymax>
                </bndbox>
        </object>
</annotation>        
