<annotation>
        <folder>FOLDER</folder>
        <filename>389733021.jpg</filename>
        <path>data/scenes/train\389733021.jpg</path>
        <source>
                <database>Unknown</database>
        </source>
        <size>
                <width>720</width>
                <height>720</height>
                <depth>3</depth>
        </size>
 <object>
                <name>GO</name>
                <pose>Unspecified</pose>
                <truncated>0</truncated>
                <difficult>0</difficult>
                <bndbox>
                        <xmin>316</xmin>
                        <ymin>194</ymin>
                        <xmax>347</xmax>
                        <ymax>223</ymax>
                </bndbox>
        </object>
 <object>
                <name>GO</name>
                <pose>Unspecified</pose>
                <truncated>0</truncated>
                <difficult>0</difficult>
                <bndbox>
                        <xmin>529</xmin>
                        <ymin>254</ymin>
                        <xmax>563</xmax>
                        <ymax>286</ymax>
                </bndbox>
        </object>
 <object>
                <name>E9</name>
                <pose>Unspecified</pose>
                <truncated>0</truncated>
                <difficult>0</difficult>
                <bndbox>
                        <xmin>289</xmin>
                        <ymin>455</ymin>
                        <xmax>304</xmax>
                        <ymax>494</ymax>
                </bndbox>
        </object>
 <object>
                <name>E9</name>
                <pose>Unspecified</pose>
                <truncated>0</truncated>
                <difficult>0</difficult>
                <bndbox>
                        <xmin>149</xmin>
                        <ymin>279</ymin>
                        <xmax>164</xmax>
                        <ymax>319</ymax>
                </bndbox>
        </object>
</annotation>        
