<annotation>
        <folder>FOLDER</folder>
        <filename>413567299.jpg</filename>
        <path>data/scenes/train\413567299.jpg</path>
        <source>
                <database>Unknown</database>
        </source>
        <size>
                <width>720</width>
                <height>720</height>
                <depth>3</depth>
        </size>
 <object>
                <name>E8</name>
                <pose>Unspecified</pose>
                <truncated>0</truncated>
                <difficult>0</difficult>
                <bndbox>
                        <xmin>407</xmin>
                        <ymin>395</ymin>
                        <xmax>447</xmax>
                        <ymax>447</ymax>
                </bndbox>
        </object>
 <object>
                <name>EU</name>
                <pose>Unspecified</pose>
                <truncated>0</truncated>
                <difficult>0</difficult>
                <bndbox>
                        <xmin>382</xmin>
                        <ymin>423</ymin>
                        <xmax>411</xmax>
                        <ymax>465</ymax>
                </bndbox>
        </object>
 <object>
                <name>E8</name>
                <pose>Unspecified</pose>
                <truncated>0</truncated>
                <difficult>0</difficult>
                <bndbox>
                        <xmin>292</xmin>
                        <ymin>445</ymin>
                        <xmax>316</xmax>
                        <ymax>505</ymax>
                </bndbox>
        </object>
 <object>
                <name>E8</name>
                <pose>Unspecified</pose>
                <truncated>0</truncated>
                <difficult>0</difficult>
                <bndbox>
                        <xmin>88</xmin>
                        <ymin>171</ymin>
                        <xmax>116</xmax>
                        <ymax>229</ymax>
                </bndbox>
        </object>
</annotation>        
