<annotation>
        <folder>FOLDER</folder>
        <filename>420341390.jpg</filename>
        <path>data/scenes/train\420341390.jpg</path>
        <source>
                <database>Unknown</database>
        </source>
        <size>
                <width>720</width>
                <height>720</height>
                <depth>3</depth>
        </size>
 <object>
                <name>G9</name>
                <pose>Unspecified</pose>
                <truncated>0</truncated>
                <difficult>0</difficult>
                <bndbox>
                        <xmin>387</xmin>
                        <ymin>501</ymin>
                        <xmax>404</xmax>
                        <ymax>542</ymax>
                </bndbox>
        </object>
 <object>
                <name>GO</name>
                <pose>Unspecified</pose>
                <truncated>0</truncated>
                <difficult>0</difficult>
                <bndbox>
                        <xmin>345</xmin>
                        <ymin>498</ymin>
                        <xmax>364</xmax>
                        <ymax>534</ymax>
                </bndbox>
        </object>
 <object>
                <name>EO</name>
                <pose>Unspecified</pose>
                <truncated>0</truncated>
                <difficult>0</difficult>
                <bndbox>
                        <xmin>303</xmin>
                        <ymin>489</ymin>
                        <xmax>328</xmax>
                        <ymax>522</ymax>
                </bndbox>
        </object>
 <object>
                <name>EO</name>
                <pose>Unspecified</pose>
                <truncated>0</truncated>
                <difficult>0</difficult>
                <bndbox>
                        <xmin>305</xmin>
                        <ymin>264</ymin>
                        <xmax>333</xmax>
                        <ymax>299</ymax>
                </bndbox>
        </object>
</annotation>        
