<annotation>
        <folder>FOLDER</folder>
        <filename>513208752.jpg</filename>
        <path>data/scenes/train\513208752.jpg</path>
        <source>
                <database>Unknown</database>
        </source>
        <size>
                <width>720</width>
                <height>720</height>
                <depth>3</depth>
        </size>
 <object>
                <name>S7</name>
                <pose>Unspecified</pose>
                <truncated>0</truncated>
                <difficult>0</difficult>
                <bndbox>
                        <xmin>110</xmin>
                        <ymin>157</ymin>
                        <xmax>127</xmax>
                        <ymax>198</ymax>
                </bndbox>
        </object>
 <object>
                <name>S7</name>
                <pose>Unspecified</pose>
                <truncated>0</truncated>
                <difficult>0</difficult>
                <bndbox>
                        <xmin>278</xmin>
                        <ymin>315</ymin>
                        <xmax>295</xmax>
                        <ymax>343</ymax>
                </bndbox>
        </object>
 <object>
                <name>EA</name>
                <pose>Unspecified</pose>
                <truncated>0</truncated>
                <difficult>0</difficult>
                <bndbox>
                        <xmin>568</xmin>
                        <ymin>174</ymin>
                        <xmax>599</xmax>
                        <ymax>197</ymax>
                </bndbox>
        </object>
 <object>
                <name>EA</name>
                <pose>Unspecified</pose>
                <truncated>0</truncated>
                <difficult>0</difficult>
                <bndbox>
                        <xmin>345</xmin>
                        <ymin>229</ymin>
                        <xmax>385</xmax>
                        <ymax>252</ymax>
                </bndbox>
        </object>
</annotation>        
