<annotation>
        <folder>FOLDER</folder>
        <filename>635913147.jpg</filename>
        <path>data/scenes/train\635913147.jpg</path>
        <source>
                <database>Unknown</database>
        </source>
        <size>
                <width>720</width>
                <height>720</height>
                <depth>3</depth>
        </size>
 <object>
                <name>S7</name>
                <pose>Unspecified</pose>
                <truncated>0</truncated>
                <difficult>0</difficult>
                <bndbox>
                        <xmin>566</xmin>
                        <ymin>327</ymin>
                        <xmax>612</xmax>
                        <ymax>369</ymax>
                </bndbox>
        </object>
 <object>
                <name>H8</name>
                <pose>Unspecified</pose>
                <truncated>0</truncated>
                <difficult>0</difficult>
                <bndbox>
                        <xmin>532</xmin>
                        <ymin>372</ymin>
                        <xmax>574</xmax>
                        <ymax>422</ymax>
                </bndbox>
        </object>
 <object>
                <name>HO</name>
                <pose>Unspecified</pose>
                <truncated>0</truncated>
                <difficult>0</difficult>
                <bndbox>
                        <xmin>478</xmin>
                        <ymin>410</ymin>
                        <xmax>511</xmax>
                        <ymax>468</ymax>
                </bndbox>
        </object>
 <object>
                <name>HO</name>
                <pose>Unspecified</pose>
                <truncated>0</truncated>
                <difficult>0</difficult>
                <bndbox>
                        <xmin>189</xmin>
                        <ymin>224</ymin>
                        <xmax>224</xmax>
                        <ymax>279</ymax>
                </bndbox>
        </object>
</annotation>        
