<annotation>
        <folder>FOLDER</folder>
        <filename>790532609.jpg</filename>
        <path>data/scenes/train\790532609.jpg</path>
        <source>
                <database>Unknown</database>
        </source>
        <size>
                <width>720</width>
                <height>720</height>
                <depth>3</depth>
        </size>
 <object>
                <name>H10</name>
                <pose>Unspecified</pose>
                <truncated>0</truncated>
                <difficult>0</difficult>
                <bndbox>
                        <xmin>241</xmin>
                        <ymin>343</ymin>
                        <xmax>284</xmax>
                        <ymax>397</ymax>
                </bndbox>
        </object>
 <object>
                <name>G7</name>
                <pose>Unspecified</pose>
                <truncated>0</truncated>
                <difficult>0</difficult>
                <bndbox>
                        <xmin>299</xmin>
                        <ymin>302</ymin>
                        <xmax>330</xmax>
                        <ymax>361</ymax>
                </bndbox>
        </object>
 <object>
                <name>E8</name>
                <pose>Unspecified</pose>
                <truncated>0</truncated>
                <difficult>0</difficult>
                <bndbox>
                        <xmin>350</xmin>
                        <ymin>288</ymin>
                        <xmax>380</xmax>
                        <ymax>343</ymax>
                </bndbox>
        </object>
 <object>
                <name>E8</name>
                <pose>Unspecified</pose>
                <truncated>0</truncated>
                <difficult>0</difficult>
                <bndbox>
                        <xmin>593</xmin>
                        <ymin>532</ymin>
                        <xmax>626</xmax>
                        <ymax>580</ymax>
                </bndbox>
        </object>
</annotation>        
