<annotation>
        <folder>FOLDER</folder>
        <filename>855781876.jpg</filename>
        <path>data/scenes/train\855781876.jpg</path>
        <source>
                <database>Unknown</database>
        </source>
        <size>
                <width>720</width>
                <height>720</height>
                <depth>3</depth>
        </size>
 <object>
                <name>HK</name>
                <pose>Unspecified</pose>
                <truncated>0</truncated>
                <difficult>0</difficult>
                <bndbox>
                        <xmin>390</xmin>
                        <ymin>351</ymin>
                        <xmax>420</xmax>
                        <ymax>374</ymax>
                </bndbox>
        </object>
 <object>
                <name>HK</name>
                <pose>Unspecified</pose>
                <truncated>0</truncated>
                <difficult>0</difficult>
                <bndbox>
                        <xmin>243</xmin>
                        <ymin>529</ymin>
                        <xmax>284</xmax>
                        <ymax>554</ymax>
                </bndbox>
        </object>
 <object>
                <name>GK</name>
                <pose>Unspecified</pose>
                <truncated>0</truncated>
                <difficult>0</difficult>
                <bndbox>
                        <xmin>301</xmin>
                        <ymin>171</ymin>
                        <xmax>338</xmax>
                        <ymax>202</ymax>
                </bndbox>
        </object>
 <object>
                <name>GK</name>
                <pose>Unspecified</pose>
                <truncated>0</truncated>
                <difficult>0</difficult>
                <bndbox>
                        <xmin>524</xmin>
                        <ymin>194</ymin>
                        <xmax>556</xmax>
                        <ymax>224</ymax>
                </bndbox>
        </object>
</annotation>        
