<annotation>
        <folder>FOLDER</folder>
        <filename>976114865.jpg</filename>
        <path>data/scenes/train\976114865.jpg</path>
        <source>
                <database>Unknown</database>
        </source>
        <size>
                <width>720</width>
                <height>720</height>
                <depth>3</depth>
        </size>
 <object>
                <name>S8</name>
                <pose>Unspecified</pose>
                <truncated>0</truncated>
                <difficult>0</difficult>
                <bndbox>
                        <xmin>494</xmin>
                        <ymin>567</ymin>
                        <xmax>522</xmax>
                        <ymax>608</ymax>
                </bndbox>
        </object>
 <object>
                <name>E9</name>
                <pose>Unspecified</pose>
                <truncated>0</truncated>
                <difficult>0</difficult>
                <bndbox>
                        <xmin>391</xmin>
                        <ymin>184</ymin>
                        <xmax>428</xmax>
                        <ymax>211</ymax>
                </bndbox>
        </object>
 <object>
                <name>E9</name>
                <pose>Unspecified</pose>
                <truncated>0</truncated>
                <difficult>0</difficult>
                <bndbox>
                        <xmin>295</xmin>
                        <ymin>389</ymin>
                        <xmax>326</xmax>
                        <ymax>412</ymax>
                </bndbox>
        </object>
</annotation>        
