<annotation>
        <folder>FOLDER</folder>
        <filename>045772980.jpg</filename>
        <path>data/scenes/train\045772980.jpg</path>
        <source>
                <database>Unknown</database>
        </source>
        <size>
                <width>720</width>
                <height>720</height>
                <depth>3</depth>
        </size>
 <object>
                <name>E8</name>
                <pose>Unspecified</pose>
                <truncated>0</truncated>
                <difficult>0</difficult>
                <bndbox>
                        <xmin>211</xmin>
                        <ymin>522</ymin>
                        <xmax>252</xmax>
                        <ymax>539</ymax>
                </bndbox>
        </object>
 <object>
                <name>G8</name>
                <pose>Unspecified</pose>
                <truncated>0</truncated>
                <difficult>0</difficult>
                <bndbox>
                        <xmin>211</xmin>
                        <ymin>485</ymin>
                        <xmax>246</xmax>
                        <ymax>505</ymax>
                </bndbox>
        </object>
 <object>
                <name>GK</name>
                <pose>Unspecified</pose>
                <truncated>0</truncated>
                <difficult>0</difficult>
                <bndbox>
                        <xmin>225</xmin>
                        <ymin>436</ymin>
                        <xmax>251</xmax>
                        <ymax>456</ymax>
                </bndbox>
        </object>
 <object>
                <name>GK</name>
                <pose>Unspecified</pose>
                <truncated>0</truncated>
                <difficult>0</difficult>
                <bndbox>
                        <xmin>444</xmin>
                        <ymin>403</ymin>
                        <xmax>475</xmax>
                        <ymax>425</ymax>
                </bndbox>
        </object>
</annotation>        
