<annotation>
        <folder>FOLDER</folder>
        <filename>328158649.jpg</filename>
        <path>data/scenes/train\328158649.jpg</path>
        <source>
                <database>Unknown</database>
        </source>
        <size>
                <width>720</width>
                <height>720</height>
                <depth>3</depth>
        </size>
 <object>
                <name>E10</name>
                <pose>Unspecified</pose>
                <truncated>0</truncated>
                <difficult>0</difficult>
                <bndbox>
                        <xmin>443</xmin>
                        <ymin>501</ymin>
                        <xmax>463</xmax>
                        <ymax>534</ymax>
                </bndbox>
        </object>
 <object>
                <name>G9</name>
                <pose>Unspecified</pose>
                <truncated>0</truncated>
                <difficult>0</difficult>
                <bndbox>
                        <xmin>406</xmin>
                        <ymin>499</ymin>
                        <xmax>422</xmax>
                        <ymax>534</ymax>
                </bndbox>
        </object>
 <object>
                <name>E8</name>
                <pose>Unspecified</pose>
                <truncated>0</truncated>
                <difficult>0</difficult>
                <bndbox>
                        <xmin>369</xmin>
                        <ymin>496</ymin>
                        <xmax>390</xmax>
                        <ymax>532</ymax>
                </bndbox>
        </object>
 <object>
                <name>E8</name>
                <pose>Unspecified</pose>
                <truncated>0</truncated>
                <difficult>0</difficult>
                <bndbox>
                        <xmin>326</xmin>
                        <ymin>274</ymin>
                        <xmax>346</xmax>
                        <ymax>311</ymax>
                </bndbox>
        </object>
</annotation>        
