<annotation>
        <folder>FOLDER</folder>
        <filename>472778189.jpg</filename>
        <path>data/scenes/train\472778189.jpg</path>
        <source>
                <database>Unknown</database>
        </source>
        <size>
                <width>720</width>
                <height>720</height>
                <depth>3</depth>
        </size>
 <object>
                <name>G8</name>
                <pose>Unspecified</pose>
                <truncated>0</truncated>
                <difficult>0</difficult>
                <bndbox>
                        <xmin>454</xmin>
                        <ymin>98</ymin>
                        <xmax>487</xmax>
                        <ymax>124</ymax>
                </bndbox>
        </object>
 <object>
                <name>E8</name>
                <pose>Unspecified</pose>
                <truncated>0</truncated>
                <difficult>0</difficult>
                <bndbox>
                        <xmin>366</xmin>
                        <ymin>312</ymin>
                        <xmax>407</xmax>
                        <ymax>332</ymax>
                </bndbox>
        </object>
 <object>
                <name>E8</name>
                <pose>Unspecified</pose>
                <truncated>0</truncated>
                <difficult>0</difficult>
                <bndbox>
                        <xmin>531</xmin>
                        <ymin>155</ymin>
                        <xmax>565</xmax>
                        <ymax>178</ymax>
                </bndbox>
        </object>
</annotation>        
