<annotation>
        <folder>FOLDER</folder>
        <filename>637256688.jpg</filename>
        <path>data/scenes/train\637256688.jpg</path>
        <source>
                <database>Unknown</database>
        </source>
        <size>
                <width>720</width>
                <height>720</height>
                <depth>3</depth>
        </size>
 <object>
                <name>GA</name>
                <pose>Unspecified</pose>
                <truncated>0</truncated>
                <difficult>0</difficult>
                <bndbox>
                        <xmin>278</xmin>
                        <ymin>470</ymin>
                        <xmax>334</xmax>
                        <ymax>504</ymax>
                </bndbox>
        </object>
 <object>
                <name>GA</name>
                <pose>Unspecified</pose>
                <truncated>0</truncated>
                <difficult>0</difficult>
                <bndbox>
                        <xmin>622</xmin>
                        <ymin>442</ymin>
                        <xmax>677</xmax>
                        <ymax>479</ymax>
                </bndbox>
        </object>
 <object>
                <name>SO</name>
                <pose>Unspecified</pose>
                <truncated>0</truncated>
                <difficult>0</difficult>
                <bndbox>
                        <xmin>496</xmin>
                        <ymin>302</ymin>
                        <xmax>513</xmax>
                        <ymax>331</ymax>
                </bndbox>
        </object>
 <object>
                <name>SO</name>
                <pose>Unspecified</pose>
                <truncated>0</truncated>
                <difficult>0</difficult>
                <bndbox>
                        <xmin>367</xmin>
                        <ymin>115</ymin>
                        <xmax>383</xmax>
                        <ymax>145</ymax>
                </bndbox>
        </object>
</annotation>        
