<annotation>
        <folder>FOLDER</folder>
        <filename>733229534.jpg</filename>
        <path>data/scenes/train\733229534.jpg</path>
        <source>
                <database>Unknown</database>
        </source>
        <size>
                <width>720</width>
                <height>720</height>
                <depth>3</depth>
        </size>
 <object>
                <name>E9</name>
                <pose>Unspecified</pose>
                <truncated>0</truncated>
                <difficult>0</difficult>
                <bndbox>
                        <xmin>517</xmin>
                        <ymin>604</ymin>
                        <xmax>540</xmax>
                        <ymax>648</ymax>
                </bndbox>
        </object>
 <object>
                <name>SA</name>
                <pose>Unspecified</pose>
                <truncated>0</truncated>
                <difficult>0</difficult>
                <bndbox>
                        <xmin>448</xmin>
                        <ymin>248</ymin>
                        <xmax>494</xmax>
                        <ymax>293</ymax>
                </bndbox>
        </object>
 <object>
                <name>SA</name>
                <pose>Unspecified</pose>
                <truncated>0</truncated>
                <difficult>0</difficult>
                <bndbox>
                        <xmin>282</xmin>
                        <ymin>550</ymin>
                        <xmax>325</xmax>
                        <ymax>592</ymax>
                </bndbox>
        </object>
</annotation>        
