<annotation>
        <folder>FOLDER</folder>
        <filename>764602491.jpg</filename>
        <path>data/scenes/train\764602491.jpg</path>
        <source>
                <database>Unknown</database>
        </source>
        <size>
                <width>720</width>
                <height>720</height>
                <depth>3</depth>
        </size>
 <object>
                <name>S8</name>
                <pose>Unspecified</pose>
                <truncated>0</truncated>
                <difficult>0</difficult>
                <bndbox>
                        <xmin>383</xmin>
                        <ymin>383</ymin>
                        <xmax>404</xmax>
                        <ymax>412</ymax>
                </bndbox>
        </object>
 <object>
                <name>H8</name>
                <pose>Unspecified</pose>
                <truncated>0</truncated>
                <difficult>0</difficult>
                <bndbox>
                        <xmin>421</xmin>
                        <ymin>362</ymin>
                        <xmax>438</xmax>
                        <ymax>403</ymax>
                </bndbox>
        </object>
 <object>
                <name>HO</name>
                <pose>Unspecified</pose>
                <truncated>0</truncated>
                <difficult>0</difficult>
                <bndbox>
                        <xmin>471</xmin>
                        <ymin>362</ymin>
                        <xmax>491</xmax>
                        <ymax>393</ymax>
                </bndbox>
        </object>
 <object>
                <name>HO</name>
                <pose>Unspecified</pose>
                <truncated>0</truncated>
                <difficult>0</difficult>
                <bndbox>
                        <xmin>562</xmin>
                        <ymin>565</ymin>
                        <xmax>584</xmax>
                        <ymax>600</ymax>
                </bndbox>
        </object>
</annotation>        
