<annotation>
        <folder>FOLDER</folder>
        <filename>771329825.jpg</filename>
        <path>data/scenes/train\771329825.jpg</path>
        <source>
                <database>Unknown</database>
        </source>
        <size>
                <width>720</width>
                <height>720</height>
                <depth>3</depth>
        </size>
 <object>
                <name>G10</name>
                <pose>Unspecified</pose>
                <truncated>0</truncated>
                <difficult>0</difficult>
                <bndbox>
                        <xmin>354</xmin>
                        <ymin>214</ymin>
                        <xmax>384</xmax>
                        <ymax>247</ymax>
                </bndbox>
        </object>
 <object>
                <name>S10</name>
                <pose>Unspecified</pose>
                <truncated>0</truncated>
                <difficult>0</difficult>
                <bndbox>
                        <xmin>391</xmin>
                        <ymin>188</ymin>
                        <xmax>415</xmax>
                        <ymax>225</ymax>
                </bndbox>
        </object>
 <object>
                <name>G9</name>
                <pose>Unspecified</pose>
                <truncated>0</truncated>
                <difficult>0</difficult>
                <bndbox>
                        <xmin>424</xmin>
                        <ymin>170</ymin>
                        <xmax>450</xmax>
                        <ymax>208</ymax>
                </bndbox>
        </object>
 <object>
                <name>G9</name>
                <pose>Unspecified</pose>
                <truncated>0</truncated>
                <difficult>0</difficult>
                <bndbox>
                        <xmin>591</xmin>
                        <ymin>314</ymin>
                        <xmax>615</xmax>
                        <ymax>351</ymax>
                </bndbox>
        </object>
</annotation>        
