<annotation>
        <folder>FOLDER</folder>
        <filename>895659425.jpg</filename>
        <path>data/scenes/train\895659425.jpg</path>
        <source>
                <database>Unknown</database>
        </source>
        <size>
                <width>720</width>
                <height>720</height>
                <depth>3</depth>
        </size>
 <object>
                <name>SK</name>
                <pose>Unspecified</pose>
                <truncated>0</truncated>
                <difficult>0</difficult>
                <bndbox>
                        <xmin>93</xmin>
                        <ymin>156</ymin>
                        <xmax>120</xmax>
                        <ymax>189</ymax>
                </bndbox>
        </object>
 <object>
                <name>GU</name>
                <pose>Unspecified</pose>
                <truncated>0</truncated>
                <difficult>0</difficult>
                <bndbox>
                        <xmin>64</xmin>
                        <ymin>292</ymin>
                        <xmax>103</xmax>
                        <ymax>334</ymax>
                </bndbox>
        </object>
 <object>
                <name>GU</name>
                <pose>Unspecified</pose>
                <truncated>0</truncated>
                <difficult>0</difficult>
                <bndbox>
                        <xmin>406</xmin>
                        <ymin>375</ymin>
                        <xmax>445</xmax>
                        <ymax>417</ymax>
                </bndbox>
        </object>
</annotation>        
