<annotation>
        <folder>FOLDER</folder>
        <filename>907104624.jpg</filename>
        <path>data/scenes/train\907104624.jpg</path>
        <source>
                <database>Unknown</database>
        </source>
        <size>
                <width>720</width>
                <height>720</height>
                <depth>3</depth>
        </size>
 <object>
                <name>EK</name>
                <pose>Unspecified</pose>
                <truncated>0</truncated>
                <difficult>0</difficult>
                <bndbox>
                        <xmin>430</xmin>
                        <ymin>172</ymin>
                        <xmax>449</xmax>
                        <ymax>201</ymax>
                </bndbox>
        </object>
 <object>
                <name>GA</name>
                <pose>Unspecified</pose>
                <truncated>0</truncated>
                <difficult>0</difficult>
                <bndbox>
                        <xmin>460</xmin>
                        <ymin>167</ymin>
                        <xmax>479</xmax>
                        <ymax>207</ymax>
                </bndbox>
        </object>
 <object>
                <name>S7</name>
                <pose>Unspecified</pose>
                <truncated>0</truncated>
                <difficult>0</difficult>
                <bndbox>
                        <xmin>503</xmin>
                        <ymin>177</ymin>
                        <xmax>524</xmax>
                        <ymax>205</ymax>
                </bndbox>
        </object>
 <object>
                <name>S7</name>
                <pose>Unspecified</pose>
                <truncated>0</truncated>
                <difficult>0</difficult>
                <bndbox>
                        <xmin>538</xmin>
                        <ymin>403</ymin>
                        <xmax>557</xmax>
                        <ymax>430</ymax>
                </bndbox>
        </object>
</annotation>        
