<annotation>
        <folder>FOLDER</folder>
        <filename>991106397.jpg</filename>
        <path>data/scenes/train\991106397.jpg</path>
        <source>
                <database>Unknown</database>
        </source>
        <size>
                <width>720</width>
                <height>720</height>
                <depth>3</depth>
        </size>
 <object>
                <name>S9</name>
                <pose>Unspecified</pose>
                <truncated>0</truncated>
                <difficult>0</difficult>
                <bndbox>
                        <xmin>631</xmin>
                        <ymin>400</ymin>
                        <xmax>680</xmax>
                        <ymax>443</ymax>
                </bndbox>
        </object>
 <object>
                <name>SK</name>
                <pose>Unspecified</pose>
                <truncated>0</truncated>
                <difficult>0</difficult>
                <bndbox>
                        <xmin>586</xmin>
                        <ymin>437</ymin>
                        <xmax>619</xmax>
                        <ymax>490</ymax>
                </bndbox>
        </object>
 <object>
                <name>HK</name>
                <pose>Unspecified</pose>
                <truncated>0</truncated>
                <difficult>0</difficult>
                <bndbox>
                        <xmin>530</xmin>
                        <ymin>463</ymin>
                        <xmax>564</xmax>
                        <ymax>514</ymax>
                </bndbox>
        </object>
 <object>
                <name>HK</name>
                <pose>Unspecified</pose>
                <truncated>0</truncated>
                <difficult>0</difficult>
                <bndbox>
                        <xmin>293</xmin>
                        <ymin>207</ymin>
                        <xmax>322</xmax>
                        <ymax>247</ymax>
                </bndbox>
        </object>
</annotation>        
